dominantcolors.py
dominantcolors-0.1.0.dist-info/LICENSE
dominantcolors-0.1.0.dist-info/METADATA
dominantcolors-0.1.0.dist-info/WHEEL
dominantcolors-0.1.0.dist-info/top_level.txt
dominantcolors-0.1.0.dist-info/RECORD
