Metadata-Version: 2.1
Name: dominantcolors
Version: 0.1.0
Summary: A module to grab dominant colors from image
Home-page: https://github.com/wenmin-wu/dominant-colors-py
Author: wuwenmin
Author-email: wuwenmin1991@gmail.com
License: UNKNOWN
Platform: UNKNOWN
Requires-Dist: numpy
Requires-Dist: Pillow
